{
  "id": "LanMountainDesktop.SamplePlugin",
  "name": "LanMountain Sample Plugin",
  "description": "Official sample plugin used to validate PluginSdk v5 loading, appearance, settings, and market installation.",
  "author": "LanMountainDesktop",
  "version": "0.4.0",
  "apiVersion": "5.0.0",
  "entranceAssembly": "LanMountainDesktop.SamplePlugin.dll",
  "sharedContracts": [
    {
      "id": "LanMountainDesktop.SharedContracts.SampleClock",
      "version": "2.0.0",
      "assemblyName": "LanMountainDesktop.SharedContracts.SampleClock.dll"
    }
  ],
  "runtime": {
    "mode": "in-proc"
  }
}
